{
      "nodes": [
            { "name" : "c6_Sports", "group" : 1 }, 
            { "name" : "c8_Talk", "group" : 1 }, 
            { "name" : "c10_TV", "group" : 1 }, 
            { "name" : "c3_Movies", "group" : 1 }, 
            { "name" : "c9_Together", "group" : 1 }, 
            { "name" : "c2_Games", "group" : 1 }, 
            { "name" : "c1_ConsoleGames", "group" : 1 }, 
            { "name" : "c5_Outside", "group" : 1 }, 
            { "name" : "c4_Music", "group" : 1 },
            { "name" : "Joe", "group" : 1 }, 
            { "name" : "Fiona", "group" : 1 }, 
            { "name" : "Jill", "group" : 1 }, 
            { "name" : "Bob", "group" : 1 }, 
            { "name" : "Bertha", "group" : 1 }, 
            { "name" : "Jimmy", "group" : 1 }, 
            { "name" : "Amanda", "group" : 1 }, 
            { "name" : "Dmitry", "group" : 1 }, 
            { "name" : "Scott", "group" : 1 }, 
            { "name" : "Patricia", "group" : 1 }, 
            { "name" : "Mike", "group" : 1 }, 
            { "name" : "Lois", "group" : 1 }, 
            { "name" : "Tim", "group" : 1 } 
      ], 
      "links": [
            { "source" : 1, "target" : 11, "value" : 2 }, 
            { "source" : 1, "target" : 21, "value" : 2 }, 
            { "source" : 1, "target" : 20, "value" : 1 }, 
            { "source" : 1, "target" : 19, "value" : 2 }, 
            { "source" : 2, "target" : 16, "value" : 1 }, 
            { "source" : 2, "target" : 14, "value" : 1 }, 
            { "source" : 2, "target" : 13, "value" : 1 }, 
            { "source" : 2, "target" : 15, "value" : 1 }, 
            { "source" : 2, "target" : 18, "value" : 1 }, 
            { "source" : 3, "target" : 14, "value" : 1 }, 
            { "source" : 3, "target" : 17, "value" : 1 }, 
            { "source" : 3, "target" : 21, "value" : 1 }, 
            { "source" : 3, "target" : 19, "value" : 1 }, 
            { "source" : 5, "target" : 13, "value" : 1 },
            { "source" : 5, "target" : 12, "value" : 1 },
            { "source" : 5, "target" : 10, "value" : 1 }, 
            { "source" : 5, "target" : 19, "value" : 1 }, 
            { "source" : 5, "target" : 22, "value" : 1 }, 
            { "source" : 6, "target" : 21, "value" : 1 }, 
            { "source" : 6, "target" : 20, "value" : 1 }, 
            { "source" : 7, "target" : 11, "value" : 1 }, 
            { "source" : 7, "target" : 19, "value" : 1 }, 
            { "source" : 8, "target" : 15, "value" : 1 }, 
            { "source" : 9, "target" : 17, "value" : 1 }, 
            { "source" : 9, "target" : 22, "value" : 1 } 
      ]
}